{"characters_index.md":"JH5ijIxO","characters_mine-girl.md":"gNhFbBbX","characters_noble-girl.md":"CZ678U6_","characters_protagonist.md":"BU1yKK7R","characters_punk-girl.md":"BrOjVhQ9","characters_sport-girl.md":"qtVkH-Cq","characters_sunny-girl.md":"0SY3sAZ0","guide_企劃概要.md":"DmMKggMI","index.md":"BPiAxh05","mechanics_overview.md":"DvNEvSxi","meetings_minutes.md":"Bzjd0hh5","story_dialogues.md":"BVbzdav6","story_劇情腳本_第三四天.md":"BlRaFTky","story_序章_半臉cg與番組開場台詞集.md":"ClCvOzH4","story_序章_預告片式分鏡表.md":"CFem1Bma","timeline_overview.md":"CrfaJH7g","tools_json-editor.md":"BFZ6CM6X","tools_opening-preview.md":"DmNFRc6c"}
